lexit/__init__.py
lexit-0.0.1.dist-info/METADATA
lexit-0.0.1.dist-info/RECORD
lexit-0.0.1.dist-info/WHEEL
lexit-0.0.1.dist-info/top_level.txt
