Metadata-Version: 2.1
Name: lexit
Version: 0.0.1
Summary: Lexer generation
Home-page: https://github.com/pypa/example-project
Author: Sergey Tikhonov
Author-email: srg.tikhonov@gmail.com
License: UNKNOWN
Platform: UNKNOWN
Classifier: Programming Language :: Python :: 3
Classifier: License :: OSI Approved :: MIT License
Classifier: Operating System :: OS Independent
